mcp_run_python/__init__.py
mcp_run_python/__main__.py
mcp_run_python/_cli.py
mcp_run_python/code_sandbox.py
mcp_run_python/deno/deno.jsonc
mcp_run_python/deno/deno.lock
mcp_run_python/deno/src/main.ts
mcp_run_python/deno/src/polyfill.ts
mcp_run_python/deno/src/prepareEnvCode.ts
mcp_run_python/deno/src/runCode.ts
mcp_run_python/main.py
mcp_run_python/py.typed
mcp_run_python-0.0.22.dist-info/WHEEL
mcp_run_python-0.0.22.dist-info/entry_points.txt
mcp_run_python-0.0.22.dist-info/METADATA
mcp_run_python-0.0.22.dist-info/RECORD
