Metadata-Version: 2.4
Name: mcp-run-python
Version: 0.0.22
Summary: Model Context Protocol server to run Python code in a sandbox.
Author: Samuel Colvin
Author-email: Samuel Colvin <samuel@pydantic.dev>
License-Expression: MIT
Classifier: Development Status :: 4 - Beta
Classifier: Programming Language :: Python
Classifier: Programming Language :: Python :: 3
Classifier: Programming Language :: Python :: 3 :: Only
Classifier: Programming Language :: Python :: 3.10
Classifier: Programming Language :: Python :: 3.11
Classifier: Programming Language :: Python :: 3.12
Classifier: Programming Language :: Python :: 3.13
Classifier: Programming Language :: Python :: 3.14
Classifier: Intended Audience :: Developers
Classifier: Intended Audience :: Information Technology
Classifier: Intended Audience :: System Administrators
Classifier: License :: OSI Approved :: MIT License
Classifier: Operating System :: Unix
Classifier: Operating System :: POSIX :: Linux
Classifier: Environment :: Console
Classifier: Environment :: MacOS X
Classifier: Topic :: Software Development :: Libraries :: Python Modules
Classifier: Topic :: Internet
Requires-Dist: mcp>=1.13.1
Requires-Python: >=3.10
Project-URL: Changelog, https://github.com/pydantic/mcp-run-python/releases
Project-URL: Homepage, https://github.com/pydantic/mcp-run-python
Project-URL: Source, https://github.com/pydantic/mcp-run-python
